main.py
auth/__init__.py
auth/auth_info_middleware.py
auth/credential_store.py
auth/fastmcp_google_auth.py
auth/google_auth.py
auth/google_remote_auth_provider.py
auth/mcp_session_middleware.py
auth/oauth21_session_store.py
auth/oauth_callback_server.py
auth/oauth_common_handlers.py
auth/oauth_config.py
auth/oauth_error_handling.py
auth/oauth_responses.py
auth/oauth_types.py
auth/scopes.py
auth/service_decorator.py
core/__init__.py
core/api_enablement.py
core/comments.py
core/config.py
core/context.py
core/log_formatter.py
core/server.py
core/tool_registry.py
core/tool_tier_loader.py
core/tool_tiers.yaml
core/utils.py
gcalendar/__init__.py
gcalendar/calendar_tools.py
gchat/__init__.py
gchat/chat_tools.py
gdocs/__init__.py
gdocs/docs_helpers.py
gdocs/docs_structure.py
gdocs/docs_tables.py
gdocs/docs_tools.py
gdocs/managers/__init__.py
gdocs/managers/batch_operation_manager.py
gdocs/managers/header_footer_manager.py
gdocs/managers/table_operation_manager.py
gdocs/managers/validation_manager.py
gdrive/__init__.py
gdrive/drive_helpers.py
gdrive/drive_tools.py
gforms/__init__.py
gforms/forms_tools.py
gmail/__init__.py
gmail/gmail_tools.py
gsearch/__init__.py
gsearch/search_tools.py
gsheets/__init__.py
gsheets/sheets_tools.py
gslides/__init__.py
gslides/slides_tools.py
gtasks/__init__.py
gtasks/tasks_tools.py
mseep_workspace_mcp-1.4.6.dist-info/licenses/LICENSE
mseep_workspace_mcp-1.4.6.dist-info/METADATA
mseep_workspace_mcp-1.4.6.dist-info/WHEEL
mseep_workspace_mcp-1.4.6.dist-info/entry_points.txt
mseep_workspace_mcp-1.4.6.dist-info/top_level.txt
mseep_workspace_mcp-1.4.6.dist-info/RECORD
