Metadata-Version: 2.4
Name: mseep-workspace-mcp
Version: 1.4.6
Summary: Comprehensive, highly performant Google Workspace Streamable HTTP & SSE MCP Server for Calendar, Gmail, Docs, Sheets, Slides & Drive
Author-email: mseep <support@skydeck.ai>
License: MIT
Project-URL: Homepage, https://workspacemcp.com
Project-URL: Repository, https://github.com/taylorwilsdon/google_workspace_mcp
Project-URL: Documentation, https://github.com/taylorwilsdon/google_workspace_mcp#readme
Project-URL: Issues, https://github.com/taylorwilsdon/google_workspace_mcp/issues
Project-URL: Changelog, https://github.com/taylorwilsdon/google_workspace_mcp/releases
Keywords: mcp,google,workspace,llm,ai,claude,model,context,protocol,server
Classifier: Development Status :: 4 - Beta
Classifier: Environment :: Console
Classifier: Intended Audience :: Developers
Classifier: License :: OSI Approved :: MIT License
Classifier: Natural Language :: English
Classifier: Operating System :: OS Independent
Classifier: Programming Language :: Python
Classifier: Programming Language :: Python :: 3 :: Only
Classifier: Programming Language :: Python :: 3.11
Classifier: Programming Language :: Python :: 3.12
Classifier: Topic :: Internet :: WWW/HTTP :: Dynamic Content
Classifier: Topic :: Internet :: WWW/HTTP :: HTTP Servers
Classifier: Topic :: Software Development :: Libraries :: Application Frameworks
Classifier: Topic :: Communications :: Chat
Classifier: Topic :: Office/Business
Classifier: Topic :: Scientific/Engineering :: Artificial Intelligence
Classifier: Typing :: Typed
Requires-Python: >=3.10
License-File: LICENSE
Requires-Dist: fastapi>=0.115.12
Requires-Dist: fastmcp==2.11.3
Requires-Dist: google-api-python-client>=2.168.0
Requires-Dist: google-auth-httplib2>=0.2.0
Requires-Dist: google-auth-oauthlib>=1.2.2
Requires-Dist: httpx>=0.28.1
Requires-Dist: pyjwt>=2.10.1
Requires-Dist: ruff>=0.12.4
Requires-Dist: tomlkit
Requires-Dist: aiohttp>=3.9.0
Requires-Dist: cachetools>=5.3.0
Requires-Dist: cryptography>=41.0.0
Requires-Dist: python-dotenv>=1.1.0
Provides-Extra: dev
Requires-Dist: twine>=5.0.0; extra == "dev"
Dynamic: license-file
